esdao/__init__.py
esdao/dsl.py
esdao-0.1.0.dist-info/METADATA
esdao-0.1.0.dist-info/WHEEL
esdao-0.1.0.dist-info/top_level.txt
esdao-0.1.0.dist-info/RECORD
